hvseispy/IO.py
hvseispy/__init__.py
hvseispy/misc.py
hvseispy/plot_tools.py
hvseispy/seismic.py
hvseispy/specsignal.py
hvseispy-1.0.2.dist-info/LICENSE.txt
hvseispy-1.0.2.dist-info/METADATA
hvseispy-1.0.2.dist-info/WHEEL
hvseispy-1.0.2.dist-info/entry_points.txt
hvseispy-1.0.2.dist-info/top_level.txt
hvseispy-1.0.2.dist-info/RECORD
