Metadata-Version: 2.2
Name: hvseispy
Version: 1.0.2
Summary: A Python package for Horizontal-to-Vertical Spectral Ratio (HVSR) analysis of seismic data.
Author-email: Jesús Ochoa <ochoacontrerasjesus8@gmail.com>
License: MIT
Project-URL: Homepage, https://github.com/JOchoa51/HVSeisPy
Project-URL: Repository, https://github.com/JOchoa51/HVSeisPy
Keywords: seismic,HVSR,signal-processing,geophysics
Classifier: Programming Language :: Python :: 3
Classifier: License :: OSI Approved :: MIT License
Classifier: Operating System :: OS Independent
Classifier: Development Status :: 4 - Beta
Requires-Python: >=3.6
License-File: LICENSE.txt
Requires-Dist: numpy
Requires-Dist: scipy
Requires-Dist: matplotlib
Requires-Dist: obspy
Requires-Dist: pykooh
